tgmath/__init__.py
tgmath/_const.py
tgmath/_func.py
tgmath/_trig.py
tgmath/_vec.py
tgmath-0.0.7.dist-info/METADATA
tgmath-0.0.7.dist-info/WHEEL
tgmath-0.0.7.dist-info/licenses/LICENSE
tgmath-0.0.7.dist-info/RECORD
