Metadata-Version: 2.4
Name: tgmath
Version: 0.0.7
Summary: A few useful maths functions, mainly for my personal projects.
Project-URL: Homepage, https://github.com/hardthingphantom/tgmath
Project-URL: Issues, https://github.com/hardthingphantom/tgmath/issues
Author: hardthingphantom
License-Expression: MIT
License-File: LICENSE
Classifier: Operating System :: OS Independent
Classifier: Programming Language :: Python :: 3
Requires-Python: >=3.9
